{"data":{"mdx":{"code":{"body":"function _objectWithoutProperties(source, excluded) { if (source == null) return {}; var target = _objectWithoutPropertiesLoose(source, excluded); var key, i; if (Object.getOwnPropertySymbols) { var sourceSymbolKeys = Object.getOwnPropertySymbols(source); for (i = 0; i < sourceSymbolKeys.length; i++) { key = sourceSymbolKeys[i]; if (excluded.indexOf(key) >= 0) continue; if (!Object.prototype.propertyIsEnumerable.call(source, key)) continue; target[key] = source[key]; } } return target; }\n\nfunction _objectWithoutPropertiesLoose(source, excluded) { if (source == null) return {}; var target = {}; var sourceKeys = Object.keys(source); var key, i; for (i = 0; i < sourceKeys.length; i++) { key = sourceKeys[i]; if (excluded.indexOf(key) >= 0) continue; target[key] = source[key]; } return target; }\n\nconst layoutProps = {};\nreturn class MDXContent extends React.Component {\n  constructor(props) {\n    super(props);\n    this.layout = null;\n  }\n\n  render() {\n    const _this$props = this.props,\n          {\n      components\n    } = _this$props,\n          props = _objectWithoutProperties(_this$props, [\"components\"]);\n\n    return React.createElement(MDXTag, {\n      name: \"wrapper\",\n      components: components\n    }, React.createElement(MDXTag, {\n      name: \"h2\",\n      components: components\n    }, `Color`), React.createElement(MDXTag, {\n      name: \"p\",\n      components: components\n    }, `All steps that have been completed are indicated by an outlined circle with a checkmark. The current step the user is on is indicated by a filled circle. Steps the user has not encountered yet, or future steps, are indicated by an outlined circle.`), React.createElement(MDXTag, {\n      name: \"table\",\n      components: components\n    }, React.createElement(MDXTag, {\n      name: \"thead\",\n      components: components,\n      parentName: \"table\"\n    }, React.createElement(MDXTag, {\n      name: \"tr\",\n      components: components,\n      parentName: \"thead\"\n    }, React.createElement(MDXTag, {\n      name: \"th\",\n      components: components,\n      parentName: \"tr\",\n      props: {\n        \"align\": null\n      }\n    }, `Class`), React.createElement(MDXTag, {\n      name: \"th\",\n      components: components,\n      parentName: \"tr\",\n      props: {\n        \"align\": null\n      }\n    }, `Property`), React.createElement(MDXTag, {\n      name: \"th\",\n      components: components,\n      parentName: \"tr\",\n      props: {\n        \"align\": null\n      }\n    }, `Color token`))), React.createElement(MDXTag, {\n      name: \"tbody\",\n      components: components,\n      parentName: \"table\"\n    }, React.createElement(MDXTag, {\n      name: \"tr\",\n      components: components,\n      parentName: \"tbody\"\n    }, React.createElement(MDXTag, {\n      name: \"td\",\n      components: components,\n      parentName: \"tr\",\n      props: {\n        \"align\": null\n      }\n    }, React.createElement(MDXTag, {\n      name: \"inlineCode\",\n      components: components,\n      parentName: \"td\"\n    }, `.bx--progress-step--complete svg`)), React.createElement(MDXTag, {\n      name: \"td\",\n      components: components,\n      parentName: \"tr\",\n      props: {\n        \"align\": null\n      }\n    }, `fill`), React.createElement(MDXTag, {\n      name: \"td\",\n      components: components,\n      parentName: \"tr\",\n      props: {\n        \"align\": null\n      }\n    }, React.createElement(MDXTag, {\n      name: \"inlineCode\",\n      components: components,\n      parentName: \"td\"\n    }, `\\$interactive-04`))), React.createElement(MDXTag, {\n      name: \"tr\",\n      components: components,\n      parentName: \"tbody\"\n    }, React.createElement(MDXTag, {\n      name: \"td\",\n      components: components,\n      parentName: \"tr\",\n      props: {\n        \"align\": null\n      }\n    }, React.createElement(MDXTag, {\n      name: \"inlineCode\",\n      components: components,\n      parentName: \"td\"\n    }, `.bx--progress-step--incomplete svg`)), React.createElement(MDXTag, {\n      name: \"td\",\n      components: components,\n      parentName: \"tr\",\n      props: {\n        \"align\": null\n      }\n    }, `fill`), React.createElement(MDXTag, {\n      name: \"td\",\n      components: components,\n      parentName: \"tr\",\n      props: {\n        \"align\": null\n      }\n    }, React.createElement(MDXTag, {\n      name: \"inlineCode\",\n      components: components,\n      parentName: \"td\"\n    }, `\\$interactive-04`))), React.createElement(MDXTag, {\n      name: \"tr\",\n      components: components,\n      parentName: \"tbody\"\n    }, React.createElement(MDXTag, {\n      name: \"td\",\n      components: components,\n      parentName: \"tr\",\n      props: {\n        \"align\": null\n      }\n    }, React.createElement(MDXTag, {\n      name: \"inlineCode\",\n      components: components,\n      parentName: \"td\"\n    }, `.bx--progress-step--current`), ` `, React.createElement(\"br\", null), ` `, React.createElement(MDXTag, {\n      name: \"inlineCode\",\n      components: components,\n      parentName: \"td\"\n    }, `.bx--progress-line`)), React.createElement(MDXTag, {\n      name: \"td\",\n      components: components,\n      parentName: \"tr\",\n      props: {\n        \"align\": null\n      }\n    }, `background-color`), React.createElement(MDXTag, {\n      name: \"td\",\n      components: components,\n      parentName: \"tr\",\n      props: {\n        \"align\": null\n      }\n    }, React.createElement(MDXTag, {\n      name: \"inlineCode\",\n      components: components,\n      parentName: \"td\"\n    }, `\\$interactive-04`))), React.createElement(MDXTag, {\n      name: \"tr\",\n      components: components,\n      parentName: \"tbody\"\n    }, React.createElement(MDXTag, {\n      name: \"td\",\n      components: components,\n      parentName: \"tr\",\n      props: {\n        \"align\": null\n      }\n    }, React.createElement(MDXTag, {\n      name: \"inlineCode\",\n      components: components,\n      parentName: \"td\"\n    }, `.bx--progress-step--incomplete`), ` `, React.createElement(\"br\", null), ` `, React.createElement(MDXTag, {\n      name: \"inlineCode\",\n      components: components,\n      parentName: \"td\"\n    }, `.bx--progress-line`)), React.createElement(MDXTag, {\n      name: \"td\",\n      components: components,\n      parentName: \"tr\",\n      props: {\n        \"align\": null\n      }\n    }, `background-color`), React.createElement(MDXTag, {\n      name: \"td\",\n      components: components,\n      parentName: \"tr\",\n      props: {\n        \"align\": null\n      }\n    }, React.createElement(MDXTag, {\n      name: \"inlineCode\",\n      components: components,\n      parentName: \"td\"\n    }, `\\$ui-03`))), React.createElement(MDXTag, {\n      name: \"tr\",\n      components: components,\n      parentName: \"tbody\"\n    }, React.createElement(MDXTag, {\n      name: \"td\",\n      components: components,\n      parentName: \"tr\",\n      props: {\n        \"align\": null\n      }\n    }, React.createElement(MDXTag, {\n      name: \"inlineCode\",\n      components: components,\n      parentName: \"td\"\n    }, `.bx--progress-label`)), React.createElement(MDXTag, {\n      name: \"td\",\n      components: components,\n      parentName: \"tr\",\n      props: {\n        \"align\": null\n      }\n    }, `text color`), React.createElement(MDXTag, {\n      name: \"td\",\n      components: components,\n      parentName: \"tr\",\n      props: {\n        \"align\": null\n      }\n    }, React.createElement(MDXTag, {\n      name: \"inlineCode\",\n      components: components,\n      parentName: \"td\"\n    }, `\\$text-01`))), React.createElement(MDXTag, {\n      name: \"tr\",\n      components: components,\n      parentName: \"tbody\"\n    }, React.createElement(MDXTag, {\n      name: \"td\",\n      components: components,\n      parentName: \"tr\",\n      props: {\n        \"align\": null\n      }\n    }, React.createElement(MDXTag, {\n      name: \"inlineCode\",\n      components: components,\n      parentName: \"td\"\n    }, `.bx--progress-optional`)), React.createElement(MDXTag, {\n      name: \"td\",\n      components: components,\n      parentName: \"tr\",\n      props: {\n        \"align\": null\n      }\n    }, `text color`), React.createElement(MDXTag, {\n      name: \"td\",\n      components: components,\n      parentName: \"tr\",\n      props: {\n        \"align\": null\n      }\n    }, React.createElement(MDXTag, {\n      name: \"inlineCode\",\n      components: components,\n      parentName: \"td\"\n    }, `\\$text-02`))))), React.createElement(MDXTag, {\n      name: \"h3\",\n      components: components\n    }, `Interactive states`), React.createElement(MDXTag, {\n      name: \"table\",\n      components: components\n    }, React.createElement(MDXTag, {\n      name: \"thead\",\n      components: components,\n      parentName: \"table\"\n    }, React.createElement(MDXTag, {\n      name: \"tr\",\n      components: components,\n      parentName: \"thead\"\n    }, React.createElement(MDXTag, {\n      name: \"th\",\n      components: components,\n      parentName: \"tr\",\n      props: {\n        \"align\": null\n      }\n    }, `Class`), React.createElement(MDXTag, {\n      name: \"th\",\n      components: components,\n      parentName: \"tr\",\n      props: {\n        \"align\": null\n      }\n    }, `Property`), React.createElement(MDXTag, {\n      name: \"th\",\n      components: components,\n      parentName: \"tr\",\n      props: {\n        \"align\": null\n      }\n    }, `Color token`))), React.createElement(MDXTag, {\n      name: \"tbody\",\n      components: components,\n      parentName: \"table\"\n    }, React.createElement(MDXTag, {\n      name: \"tr\",\n      components: components,\n      parentName: \"tbody\"\n    }, React.createElement(MDXTag, {\n      name: \"td\",\n      components: components,\n      parentName: \"tr\",\n      props: {\n        \"align\": null\n      }\n    }, React.createElement(MDXTag, {\n      name: \"inlineCode\",\n      components: components,\n      parentName: \"td\"\n    }, `.bx--progress-step:focus`)), React.createElement(MDXTag, {\n      name: \"td\",\n      components: components,\n      parentName: \"tr\",\n      props: {\n        \"align\": null\n      }\n    }, `border`), React.createElement(MDXTag, {\n      name: \"td\",\n      components: components,\n      parentName: \"tr\",\n      props: {\n        \"align\": null\n      }\n    }, React.createElement(MDXTag, {\n      name: \"inlineCode\",\n      components: components,\n      parentName: \"td\"\n    }, `\\$focus`))), React.createElement(MDXTag, {\n      name: \"tr\",\n      components: components,\n      parentName: \"tbody\"\n    }, React.createElement(MDXTag, {\n      name: \"td\",\n      components: components,\n      parentName: \"tr\",\n      props: {\n        \"align\": null\n      }\n    }, React.createElement(MDXTag, {\n      name: \"inlineCode\",\n      components: components,\n      parentName: \"td\"\n    }, `.bx--progress-label:hover`)), React.createElement(MDXTag, {\n      name: \"td\",\n      components: components,\n      parentName: \"tr\",\n      props: {\n        \"align\": null\n      }\n    }, `text color`), React.createElement(MDXTag, {\n      name: \"td\",\n      components: components,\n      parentName: \"tr\",\n      props: {\n        \"align\": null\n      }\n    }, React.createElement(MDXTag, {\n      name: \"inlineCode\",\n      components: components,\n      parentName: \"td\"\n    }, `\\$link-01`))), React.createElement(MDXTag, {\n      name: \"tr\",\n      components: components,\n      parentName: \"tbody\"\n    }, React.createElement(MDXTag, {\n      name: \"td\",\n      components: components,\n      parentName: \"tr\",\n      props: {\n        \"align\": null\n      }\n    }, React.createElement(MDXTag, {\n      name: \"inlineCode\",\n      components: components,\n      parentName: \"td\"\n    }, `.bx--progress__warning`)), React.createElement(MDXTag, {\n      name: \"td\",\n      components: components,\n      parentName: \"tr\",\n      props: {\n        \"align\": null\n      }\n    }, `fill`), React.createElement(MDXTag, {\n      name: \"td\",\n      components: components,\n      parentName: \"tr\",\n      props: {\n        \"align\": null\n      }\n    }, React.createElement(MDXTag, {\n      name: \"inlineCode\",\n      components: components,\n      parentName: \"td\"\n    }, `\\$support-01`))))), React.createElement(ImageComponent, {\n      fixed: \"default\",\n      caption: \"Examples of current, completed, and future steps for progress indicator\"\n    }, React.createElement(\"span\", {\n      className: \"gatsby-resp-image-wrapper\",\n      style: {\n        \"position\": \"relative\",\n        \"display\": \"block\",\n        \"maxWidth\": \"1120px\",\n        \"marginLeft\": \"auto\",\n        \"marginRight\": \"auto\"\n      }\n    }, React.createElement(\"span\", {\n      className: \"gatsby-resp-image-background-image\",\n      style: {\n        \"paddingBottom\": \"46.19565217391305%\",\n        \"position\": \"relative\",\n        \"bottom\": \"0px\",\n        \"left\": \"0px\",\n        \"backgroundSize\": \"cover\",\n        \"display\": \"block\"\n      }\n    }), React.createElement(\"img\", {\n      className: \"gatsby-resp-image-image\",\n      style: {\n        \"width\": \"100%\",\n        \"height\": \"100%\",\n        \"margin\": \"0px\",\n        \"verticalAlign\": \"middle\",\n        \"position\": \"absolute\",\n        \"top\": \"0px\",\n        \"left\": \"0px\",\n        \"boxShadow\": \"inset 0px 0px 0px 400px transparent\"\n      },\n      alt: \"Examples of current, completed, and future steps for progress indicator\",\n      title: \"\",\n      src: \"/static/78e285de1362d8267ec7796e2f3c4158/24bd0/progress-indicator-style-1.png\",\n      srcSet: \"/static/78e285de1362d8267ec7796e2f3c4158/7cb4c/progress-indicator-style-1.png 280w,\\n/static/78e285de1362d8267ec7796e2f3c4158/7ff44/progress-indicator-style-1.png 560w,\\n/static/78e285de1362d8267ec7796e2f3c4158/24bd0/progress-indicator-style-1.png 1120w,\\n/static/78e285de1362d8267ec7796e2f3c4158/b4af2/progress-indicator-style-1.png 1472w\",\n      sizes: \"(max-width: 1120px) 100vw, 1120px\"\n    }))), React.createElement(MDXTag, {\n      name: \"h2\",\n      components: components\n    }, `Typography`), React.createElement(MDXTag, {\n      name: \"p\",\n      components: components\n    }, `Labels should be one to two words only, with a limit of 16 characters total per label. All labels should be set in sentence case.`), React.createElement(MDXTag, {\n      name: \"table\",\n      components: components\n    }, React.createElement(MDXTag, {\n      name: \"thead\",\n      components: components,\n      parentName: \"table\"\n    }, React.createElement(MDXTag, {\n      name: \"tr\",\n      components: components,\n      parentName: \"thead\"\n    }, React.createElement(MDXTag, {\n      name: \"th\",\n      components: components,\n      parentName: \"tr\",\n      props: {\n        \"align\": null\n      }\n    }, `Class`), React.createElement(MDXTag, {\n      name: \"th\",\n      components: components,\n      parentName: \"tr\",\n      props: {\n        \"align\": null\n      }\n    }, `Font-size (px/rem)`), React.createElement(MDXTag, {\n      name: \"th\",\n      components: components,\n      parentName: \"tr\",\n      props: {\n        \"align\": null\n      }\n    }, `Font-weight`), React.createElement(MDXTag, {\n      name: \"th\",\n      components: components,\n      parentName: \"tr\",\n      props: {\n        \"align\": null\n      }\n    }, `Type token`))), React.createElement(MDXTag, {\n      name: \"tbody\",\n      components: components,\n      parentName: \"table\"\n    }, React.createElement(MDXTag, {\n      name: \"tr\",\n      components: components,\n      parentName: \"tbody\"\n    }, React.createElement(MDXTag, {\n      name: \"td\",\n      components: components,\n      parentName: \"tr\",\n      props: {\n        \"align\": null\n      }\n    }, React.createElement(MDXTag, {\n      name: \"inlineCode\",\n      components: components,\n      parentName: \"td\"\n    }, `.bx--progress-label`)), React.createElement(MDXTag, {\n      name: \"td\",\n      components: components,\n      parentName: \"tr\",\n      props: {\n        \"align\": null\n      }\n    }, `14 / 0.875`), React.createElement(MDXTag, {\n      name: \"td\",\n      components: components,\n      parentName: \"tr\",\n      props: {\n        \"align\": null\n      }\n    }, `Regular / 400`), React.createElement(MDXTag, {\n      name: \"td\",\n      components: components,\n      parentName: \"tr\",\n      props: {\n        \"align\": null\n      }\n    }, React.createElement(MDXTag, {\n      name: \"inlineCode\",\n      components: components,\n      parentName: \"td\"\n    }, `\\$body-short-01`))), React.createElement(MDXTag, {\n      name: \"tr\",\n      components: components,\n      parentName: \"tbody\"\n    }, React.createElement(MDXTag, {\n      name: \"td\",\n      components: components,\n      parentName: \"tr\",\n      props: {\n        \"align\": null\n      }\n    }, React.createElement(MDXTag, {\n      name: \"inlineCode\",\n      components: components,\n      parentName: \"td\"\n    }, `.bx--progress-optional`)), React.createElement(MDXTag, {\n      name: \"td\",\n      components: components,\n      parentName: \"tr\",\n      props: {\n        \"align\": null\n      }\n    }, `14 / 0.875`), React.createElement(MDXTag, {\n      name: \"td\",\n      components: components,\n      parentName: \"tr\",\n      props: {\n        \"align\": null\n      }\n    }, `Regular / 400`), React.createElement(MDXTag, {\n      name: \"td\",\n      components: components,\n      parentName: \"tr\",\n      props: {\n        \"align\": null\n      }\n    }, React.createElement(MDXTag, {\n      name: \"inlineCode\",\n      components: components,\n      parentName: \"td\"\n    }, `\\$label-01`))))), React.createElement(MDXTag, {\n      name: \"h2\",\n      components: components\n    }, `Structure`), React.createElement(MDXTag, {\n      name: \"p\",\n      components: components\n    }, `The checkmark icon can be found in the `, React.createElement(MDXTag, {\n      name: \"a\",\n      components: components,\n      parentName: \"p\",\n      props: {\n        \"href\": \"/style/iconography/library\"\n      }\n    }, `iconography`), ` library.`), React.createElement(MDXTag, {\n      name: \"table\",\n      components: components\n    }, React.createElement(MDXTag, {\n      name: \"thead\",\n      components: components,\n      parentName: \"table\"\n    }, React.createElement(MDXTag, {\n      name: \"tr\",\n      components: components,\n      parentName: \"thead\"\n    }, React.createElement(MDXTag, {\n      name: \"th\",\n      components: components,\n      parentName: \"tr\",\n      props: {\n        \"align\": null\n      }\n    }, `Class`), React.createElement(MDXTag, {\n      name: \"th\",\n      components: components,\n      parentName: \"tr\",\n      props: {\n        \"align\": null\n      }\n    }, `Property`), React.createElement(MDXTag, {\n      name: \"th\",\n      components: components,\n      parentName: \"tr\",\n      props: {\n        \"align\": null\n      }\n    }, `px / rem`), React.createElement(MDXTag, {\n      name: \"th\",\n      components: components,\n      parentName: \"tr\",\n      props: {\n        \"align\": null\n      }\n    }, `Spacing token`))), React.createElement(MDXTag, {\n      name: \"tbody\",\n      components: components,\n      parentName: \"table\"\n    }, React.createElement(MDXTag, {\n      name: \"tr\",\n      components: components,\n      parentName: \"tbody\"\n    }, React.createElement(MDXTag, {\n      name: \"td\",\n      components: components,\n      parentName: \"tr\",\n      props: {\n        \"align\": null\n      }\n    }, React.createElement(MDXTag, {\n      name: \"inlineCode\",\n      components: components,\n      parentName: \"td\"\n    }, `.bx--progress-step`)), React.createElement(MDXTag, {\n      name: \"td\",\n      components: components,\n      parentName: \"tr\",\n      props: {\n        \"align\": null\n      }\n    }, `min-width`), React.createElement(MDXTag, {\n      name: \"td\",\n      components: components,\n      parentName: \"tr\",\n      props: {\n        \"align\": null\n      }\n    }, `128 / 8`), React.createElement(MDXTag, {\n      name: \"td\",\n      components: components,\n      parentName: \"tr\",\n      props: {\n        \"align\": null\n      }\n    }, `–`)), React.createElement(MDXTag, {\n      name: \"tr\",\n      components: components,\n      parentName: \"tbody\"\n    }, React.createElement(MDXTag, {\n      name: \"td\",\n      components: components,\n      parentName: \"tr\",\n      props: {\n        \"align\": null\n      }\n    }, React.createElement(MDXTag, {\n      name: \"inlineCode\",\n      components: components,\n      parentName: \"td\"\n    }, `.bx--progress-step svg`)), React.createElement(MDXTag, {\n      name: \"td\",\n      components: components,\n      parentName: \"tr\",\n      props: {\n        \"align\": null\n      }\n    }, `height, width`), React.createElement(MDXTag, {\n      name: \"td\",\n      components: components,\n      parentName: \"tr\",\n      props: {\n        \"align\": null\n      }\n    }, `16 / 1`), React.createElement(MDXTag, {\n      name: \"td\",\n      components: components,\n      parentName: \"tr\",\n      props: {\n        \"align\": null\n      }\n    }, `–`)), React.createElement(MDXTag, {\n      name: \"tr\",\n      components: components,\n      parentName: \"tbody\"\n    }, React.createElement(MDXTag, {\n      name: \"td\",\n      components: components,\n      parentName: \"tr\",\n      props: {\n        \"align\": null\n      }\n    }, React.createElement(MDXTag, {\n      name: \"inlineCode\",\n      components: components,\n      parentName: \"td\"\n    }, `.bx--progress-step svg`)), React.createElement(MDXTag, {\n      name: \"td\",\n      components: components,\n      parentName: \"tr\",\n      props: {\n        \"align\": null\n      }\n    }, `margin-top, margin-right`), React.createElement(MDXTag, {\n      name: \"td\",\n      components: components,\n      parentName: \"tr\",\n      props: {\n        \"align\": null\n      }\n    }, `16 / 1`), React.createElement(MDXTag, {\n      name: \"td\",\n      components: components,\n      parentName: \"tr\",\n      props: {\n        \"align\": null\n      }\n    }, React.createElement(MDXTag, {\n      name: \"inlineCode\",\n      components: components,\n      parentName: \"td\"\n    }, `\\$spacing-05`))), React.createElement(MDXTag, {\n      name: \"tr\",\n      components: components,\n      parentName: \"tbody\"\n    }, React.createElement(MDXTag, {\n      name: \"td\",\n      components: components,\n      parentName: \"tr\",\n      props: {\n        \"align\": null\n      }\n    }, React.createElement(MDXTag, {\n      name: \"inlineCode\",\n      components: components,\n      parentName: \"td\"\n    }, `.bx--progress-label`)), React.createElement(MDXTag, {\n      name: \"td\",\n      components: components,\n      parentName: \"tr\",\n      props: {\n        \"align\": null\n      }\n    }, `margin-top`), React.createElement(MDXTag, {\n      name: \"td\",\n      components: components,\n      parentName: \"tr\",\n      props: {\n        \"align\": null\n      }\n    }, `16 / 1`), React.createElement(MDXTag, {\n      name: \"td\",\n      components: components,\n      parentName: \"tr\",\n      props: {\n        \"align\": null\n      }\n    }, React.createElement(MDXTag, {\n      name: \"inlineCode\",\n      components: components,\n      parentName: \"td\"\n    }, `\\$spacing-05`))))), React.createElement(ImageComponent, {\n      fixed: \"default\",\n      caption: \"Structure and spacing measurements for progress indicator | px / rem\"\n    }, React.createElement(\"span\", {\n      className: \"gatsby-resp-image-wrapper\",\n      style: {\n        \"position\": \"relative\",\n        \"display\": \"block\",\n        \"maxWidth\": \"1120px\",\n        \"marginLeft\": \"auto\",\n        \"marginRight\": \"auto\"\n      }\n    }, React.createElement(\"span\", {\n      className: \"gatsby-resp-image-background-image\",\n      style: {\n        \"paddingBottom\": \"31.38586956521739%\",\n        \"position\": \"relative\",\n        \"bottom\": \"0px\",\n        \"left\": \"0px\",\n        \"backgroundSize\": \"cover\",\n        \"display\": \"block\"\n      }\n    }), React.createElement(\"img\", {\n      className: \"gatsby-resp-image-image\",\n      style: {\n        \"width\": \"100%\",\n        \"height\": \"100%\",\n        \"margin\": \"0px\",\n        \"verticalAlign\": \"middle\",\n        \"position\": \"absolute\",\n        \"top\": \"0px\",\n        \"left\": \"0px\",\n        \"boxShadow\": \"inset 0px 0px 0px 400px transparent\"\n      },\n      alt: \"Structure and spacing for progress indicator\",\n      title: \"\",\n      src: \"/static/91a3acf1fcae77afbd7cc0049870defd/24bd0/progress-indicator-style-2.png\",\n      srcSet: \"/static/91a3acf1fcae77afbd7cc0049870defd/7cb4c/progress-indicator-style-2.png 280w,\\n/static/91a3acf1fcae77afbd7cc0049870defd/7ff44/progress-indicator-style-2.png 560w,\\n/static/91a3acf1fcae77afbd7cc0049870defd/24bd0/progress-indicator-style-2.png 1120w,\\n/static/91a3acf1fcae77afbd7cc0049870defd/b4af2/progress-indicator-style-2.png 1472w\",\n      sizes: \"(max-width: 1120px) 100vw, 1120px\"\n    }))), React.createElement(MDXTag, {\n      name: \"h3\",\n      components: components\n    }, `Recommended`), React.createElement(MDXTag, {\n      name: \"p\",\n      components: components\n    }, `The following specs are not built into the progress indicator component but are recommended by design as the proper amount between progress indicator elements.`), React.createElement(MDXTag, {\n      name: \"table\",\n      components: components\n    }, React.createElement(MDXTag, {\n      name: \"thead\",\n      components: components,\n      parentName: \"table\"\n    }, React.createElement(MDXTag, {\n      name: \"tr\",\n      components: components,\n      parentName: \"thead\"\n    }, React.createElement(MDXTag, {\n      name: \"th\",\n      components: components,\n      parentName: \"tr\",\n      props: {\n        \"align\": null\n      }\n    }, `Class`), React.createElement(MDXTag, {\n      name: \"th\",\n      components: components,\n      parentName: \"tr\",\n      props: {\n        \"align\": null\n      }\n    }, `Property`), React.createElement(MDXTag, {\n      name: \"th\",\n      components: components,\n      parentName: \"tr\",\n      props: {\n        \"align\": null\n      }\n    }, `px / rem`), React.createElement(MDXTag, {\n      name: \"th\",\n      components: components,\n      parentName: \"tr\",\n      props: {\n        \"align\": null\n      }\n    }, `Spacing token`))), React.createElement(MDXTag, {\n      name: \"tbody\",\n      components: components,\n      parentName: \"table\"\n    }, React.createElement(MDXTag, {\n      name: \"tr\",\n      components: components,\n      parentName: \"tbody\"\n    }, React.createElement(MDXTag, {\n      name: \"td\",\n      components: components,\n      parentName: \"tr\",\n      props: {\n        \"align\": null\n      }\n    }, React.createElement(MDXTag, {\n      name: \"inlineCode\",\n      components: components,\n      parentName: \"td\"\n    }, `.bx--progress`)), React.createElement(MDXTag, {\n      name: \"td\",\n      components: components,\n      parentName: \"tr\",\n      props: {\n        \"align\": null\n      }\n    }, `margin`), React.createElement(MDXTag, {\n      name: \"td\",\n      components: components,\n      parentName: \"tr\",\n      props: {\n        \"align\": null\n      }\n    }, `16 / 1`), React.createElement(MDXTag, {\n      name: \"td\",\n      components: components,\n      parentName: \"tr\",\n      props: {\n        \"align\": null\n      }\n    }, React.createElement(MDXTag, {\n      name: \"inlineCode\",\n      components: components,\n      parentName: \"td\"\n    }, `\\$spacing-05`))))), React.createElement(ImageComponent, {\n      fixed: \"default\",\n      caption: \"Recommended structure and spacing measurements for progress indicator | px / rem\"\n    }, React.createElement(\"span\", {\n      className: \"gatsby-resp-image-wrapper\",\n      style: {\n        \"position\": \"relative\",\n        \"display\": \"block\",\n        \"maxWidth\": \"1120px\",\n        \"marginLeft\": \"auto\",\n        \"marginRight\": \"auto\"\n      }\n    }, React.createElement(\"span\", {\n      className: \"gatsby-resp-image-background-image\",\n      style: {\n        \"paddingBottom\": \"32.065217391304344%\",\n        \"position\": \"relative\",\n        \"bottom\": \"0px\",\n        \"left\": \"0px\",\n        \"backgroundSize\": \"cover\",\n        \"display\": \"block\"\n      }\n    }), React.createElement(\"img\", {\n      className: \"gatsby-resp-image-image\",\n      style: {\n        \"width\": \"100%\",\n        \"height\": \"100%\",\n        \"margin\": \"0px\",\n        \"verticalAlign\": \"middle\",\n        \"position\": \"absolute\",\n        \"top\": \"0px\",\n        \"left\": \"0px\",\n        \"boxShadow\": \"inset 0px 0px 0px 400px transparent\"\n      },\n      alt: \"Structure and spacing for progress indicator\",\n      title: \"\",\n      src: \"/static/601b3679ba089f7f64734cd6a447faae/24bd0/progress-indicator-style-3.png\",\n      srcSet: \"/static/601b3679ba089f7f64734cd6a447faae/7cb4c/progress-indicator-style-3.png 280w,\\n/static/601b3679ba089f7f64734cd6a447faae/7ff44/progress-indicator-style-3.png 560w,\\n/static/601b3679ba089f7f64734cd6a447faae/24bd0/progress-indicator-style-3.png 1120w,\\n/static/601b3679ba089f7f64734cd6a447faae/b4af2/progress-indicator-style-3.png 1472w\",\n      sizes: \"(max-width: 1120px) 100vw, 1120px\"\n    }))));\n  }\n\n}"},"fields":{"slug":"/components/progress-indicator/style","currentPage":"style"},"frontmatter":{"title":"Progress indicator","label":null,"tabs":["Code","Usage","Style"],"internal":null}}},"pageContext":{"slug":"/components/progress-indicator/style","currentPage":"style"}}